viraliq.py
viraliq-0.1.2.dist-info/LICENSE
viraliq-0.1.2.dist-info/METADATA
viraliq-0.1.2.dist-info/WHEEL
viraliq-0.1.2.dist-info/entry_points.txt
viraliq-0.1.2.dist-info/top_level.txt
viraliq-0.1.2.dist-info/RECORD
