Metadata-Version: 2.1
Name: viraliq
Version: 0.1.2
Summary: Search for videos using an image query.
Home-page: https://github.com/Aveek-Saha/VIRALIQ
Author: Aveek Saha
Author-email: aveek.s98@gmail.com
License: UNKNOWN
Platform: UNKNOWN
License-File: LICENSE
Requires-Dist: Click
Requires-Dist: tensorflow (==2.6.0)
Requires-Dist: scikit-learn
Requires-Dist: numpy
Requires-Dist: tqdm
